okx_integrator/__init__.py
okx_integrator/example.py
okx_integrator/http2_example.py
okx_integrator/okx/Account_api.py
okx_integrator/okx/Broker_api.py
okx_integrator/okx/Convert_api.py
okx_integrator/okx/Copytrading_api.py
okx_integrator/okx/FDBroker_api.py
okx_integrator/okx/Finance_api.py
okx_integrator/okx/Funding_api.py
okx_integrator/okx/Market_api.py
okx_integrator/okx/Public_api.py
okx_integrator/okx/Recurring_api.py
okx_integrator/okx/Rfq_api.py
okx_integrator/okx/Trade_api.py
okx_integrator/okx/TradingBot_api.py
okx_integrator/okx/TradingData_api.py
okx_integrator/okx/__init__.py
okx_integrator/okx/client.py
okx_integrator/okx/consts.py
okx_integrator/okx/exceptions.py
okx_integrator/okx/status_api.py
okx_integrator/okx/subAccount_api.py
okx_integrator/okx/utils.py
okx_integrator/okx_http2/Account_api.py
okx_integrator/okx_http2/Convert_api.py
okx_integrator/okx_http2/Funding_api.py
okx_integrator/okx_http2/Market_api.py
okx_integrator/okx_http2/Public_api.py
okx_integrator/okx_http2/Trade_api.py
okx_integrator/okx_http2/TradingData_api.py
okx_integrator/okx_http2/__init__.py
okx_integrator/okx_http2/client.py
okx_integrator/okx_http2/consts.py
okx_integrator/okx_http2/exceptions.py
okx_integrator/okx_http2/status_api.py
okx_integrator/okx_http2/subAccount_api.py
okx_integrator/okx_http2/utils.py
okx_integrator/websocket_example.py
okx_integrator-0.1.1.dist-info/LICENSE
okx_integrator-0.1.1.dist-info/METADATA
okx_integrator-0.1.1.dist-info/WHEEL
okx_integrator-0.1.1.dist-info/RECORD
