Metadata-Version: 2.1
Name: okx-integrator
Version: 0.1.1
Summary: 
Author: Dexter
Author-email: wbolivar@dexterdevelopment.io
Requires-Python: >=3.8.10,<4.0.0
Classifier: Programming Language :: Python :: 3
Classifier: Programming Language :: Python :: 3.9
Classifier: Programming Language :: Python :: 3.10
Classifier: Programming Language :: Python :: 3.11
Requires-Dist: requests (>=2.28.2,<3.0.0)
Requires-Dist: websockets (>=11.0.2,<12.0.0)
